{
  "date": "2026-04-04",
  "cards": [
    {
      "code": "w13",
      "name": "Queen of Wands",
      "upright": true,
      "interpretation": "confident, self-assured, passionate, determined, social, charismatic, vivacious, optimistic"
    },
    {
      "code": "12",
      "name": "\u2169\u2161 The Hanged Man",
      "upright": true,
      "interpretation": "sacrifice, waiting, uncertainty, lack of direction, perspective, contemplation"
    },
    {
      "code": "s5",
      "name": "5 of Swords, reversed",
      "upright": false,
      "interpretation": "reconciliation, resolution, compromise, revenge, regret, remorse, cutting losses"
    }
  ]
}
