{
  "date": "2026-05-14",
  "cards": [
    {
      "code": "p1",
      "name": "Ace of Pentacles",
      "upright": true,
      "interpretation": "new opportunities, resources, abundance, prosperity, security, stability, manifestation"
    },
    {
      "code": "w14",
      "name": "King of Wands",
      "upright": true,
      "interpretation": "leadership, vision, big picture, taking control, daring decisions, boldness, optimism"
    },
    {
      "code": "c11",
      "name": "Page of Cups, reversed",
      "upright": false,
      "interpretation": "emotional vulnerability, immaturity, neglecting inner child, escapism, insecurity"
    }
  ]
}
