{
  "date": "2025-07-25",
  "cards": [
    {
      "code": "p2",
      "name": "2 of Pentacles",
      "upright": true,
      "interpretation": "balancing resources, adaptation, resourcefulness, flexibility, stretching resources"
    },
    {
      "code": "s4",
      "name": "4 of Swords, reversed",
      "upright": false,
      "interpretation": "recovery, awakening, re-entering world, release from isolation, restlessness, burnout"
    },
    {
      "code": "s13",
      "name": "Queen of Swords, reversed",
      "upright": false,
      "interpretation": "pessimistic, malicious, manipulative, harsh, bitter, spiteful, cruel, deceitful, unforgiving"
    }
  ]
}
