{
  "date": "2025-11-13",
  "cards": [
    {
      "code": "12",
      "name": "\u2169\u2161 The Hanged Man",
      "upright": true,
      "interpretation": "sacrifice, waiting, uncertainty, lack of direction, perspective, contemplation"
    },
    {
      "code": "s2",
      "name": "2 of Swords, reversed",
      "upright": false,
      "interpretation": "indecision, hesitancy, anxiety, too much information, no right choice, truth revealed"
    },
    {
      "code": "10",
      "name": "\u2169 Wheel of Fortune, reversed",
      "upright": false,
      "interpretation": "bad luck, lack of control, clinging to control, unwelcome changes, delays"
    }
  ]
}
