{
  "date": "2025-07-21",
  "cards": [
    {
      "code": "8",
      "name": "\u2167 Strength",
      "upright": true,
      "interpretation": "courage, bravery, confidence, compassion, self-confidence, inner power"
    },
    {
      "code": "p9",
      "name": "9 of Pentacles, reversed",
      "upright": false,
      "interpretation": "being guarded, living beyond means, material instability, reckless spending, superficiality"
    },
    {
      "code": "s8",
      "name": "8 of Swords, reversed",
      "upright": false,
      "interpretation": "freedom, release, taking control, survivor, facing fears, empowered, surrender"
    }
  ]
}
