{
  "date": "2026-03-21",
  "cards": [
    {
      "code": "12",
      "name": "\u2169\u2161 The Hanged Man",
      "upright": true,
      "interpretation": "sacrifice, waiting, uncertainty, lack of direction, perspective, contemplation"
    },
    {
      "code": "w6",
      "name": "6 of Wands",
      "upright": true,
      "interpretation": "success, victory, triumph, rewards, recognition, praise, acclaim, pride"
    },
    {
      "code": "p8",
      "name": "8 of Pentacles",
      "upright": true,
      "interpretation": "skill, talent, craftsmanship, quality, high standards, expertise, mastery, commitment, dedication, accomplishment"
    }
  ]
}
